myla/__init__.py
myla/__main__.py
myla/_api.py
myla/_auth.py
myla/_entry.py
myla/_env.py
myla/_llm.py
myla/_logging.py
myla/_models.py
myla/_run_scheduler.py
myla/_tools.py
myla/_version.py
myla/assistants.py
myla/files.py
myla/iur.py
myla/messages.py
myla/permissions.py
myla/persistence.py
myla/projects.py
myla/retrieval.py
myla/runs.py
myla/threads.py
myla/tools.py
myla/users.py
myla/utils.py
myla/extensions/__init__.py
myla/extensions/tools/__init__.py
myla/extensions/tools/qa_retrieval.py
myla/extensions/tools/qa_summary.py
myla/extensions/tools/rephrase.py
myla/llms/__init__.py
myla/llms/backend.py
myla/llms/chatglm.py
myla/llms/mock.py
myla/llms/openai.py
myla/llms/utils.py
myla/vectorstores/__init__.py
myla/vectorstores/_base.py
myla/vectorstores/_embeddings.py
myla/vectorstores/chromadb_vectorstore.py
myla/vectorstores/faiss_group.py
myla/vectorstores/faiss_vectorstore.py
myla/vectorstores/lancedb_vectorstore.py
myla/vectorstores/loaders.py
myla/vectorstores/pandas_loader.py
myla/vectorstores/pdf_loader.py
myla/vectorstores/sentence_transformers_embeddings.py
myla/vectorstores/xinference_embeddings.py
myla/webui/__init__.py
myla/webui/_web_template.py
myla/webui/__pycache__/__init__.cpython-311.pyc
myla/webui/__pycache__/__init__.cpython-39.pyc
myla/webui/__pycache__/_web_template.cpython-311.pyc
myla/webui/statics/welcome.md
myla/webui/statics/aify/aify.css
myla/webui/statics/aify/aify.js
myla/webui/statics/images/screenshot.png
myla/webui/templates/index.html
tests/__init__.py
tests/myla/__init__.py
tests/myla/assistants_test.py
tests/myla/files_test.py
tests/myla/persistence_test.py
tests/myla/threads_test.py
tests/myla/users_test.py
tests/myla/utils_test.py
tests/myla/llms/__init__.py
tests/myla/llms/mock_test.py
tests/myla/vectorstores/__init__.py
tests/myla/vectorstores/faiss_group_test.py
tests/myla/vectorstores/record_test.py
tests/myla/vectorstores/xinference_embeddings_test.py
tests/tools/__init__.py
tests/tools/sync_tool.py
myla-0.2.40.dist-info/LICENSE
myla-0.2.40.dist-info/METADATA
myla-0.2.40.dist-info/WHEEL
myla-0.2.40.dist-info/entry_points.txt
myla-0.2.40.dist-info/top_level.txt
myla-0.2.40.dist-info/RECORD
