Metadata-Version: 2.1
Name: myla
Version: 0.2.40
Summary: A local implementation of OpenAI Assistants API: Myla stands for MY Local Assistant
Home-page: https://github.com/muyuworks/myla
Author: shellc
Author-email: shenggong.wang@gmail.com
License: MIT
Keywords: AI assistant,LLM,Myla,chatbot
Classifier: Programming Language :: Python :: 3
Requires-Python: >=3.9
License-File: LICENSE
Requires-Dist: uvicorn
Requires-Dist: starlette
Requires-Dist: fastapi
Requires-Dist: python-dotenv
Requires-Dist: jinja2
Requires-Dist: aiohttp
Requires-Dist: sqlmodel
Requires-Dist: openai
Requires-Dist: python-multipart
Requires-Dist: pandas
Requires-Dist: aiofiles
Requires-Dist: sentence-transformers
Requires-Dist: faiss-cpu
Requires-Dist: Authlib
